unicornhatsimulator/__init__.py
unicornhatsimulator/clock.py
unicornhatsimulator/rotation_test.py
unicornhatsimulator/sampleHD.py
unicornhatsimulator/samplePHAT.py
unicornhatsimulator/sampleSD.py
unicornhatsimulator-1.0.4.dist-info/METADATA
unicornhatsimulator-1.0.4.dist-info/WHEEL
unicornhatsimulator-1.0.4.dist-info/licenses/LICENSE
unicornhatsimulator-1.0.4.dist-info/RECORD
