Metadata-Version: 2.1
Name: unicornhatsimulator
Version: 1.0.4
Summary: Pimoroni UnicornHAT simulator (pHAT, HAT and HAT HD)
Project-URL: Homepage, https://pypi.org/project/unicornhatsimulator/
Project-URL: Source, https://github.com/MisterBrash/unicornhatsimulator
Project-URL: Bug Tracker, https://github.com/MisterBrash/unicornhatsimulator/issues
Author-email: Matthew Brash <matthew.brash@ocsb.ca>
License-File: LICENSE
Classifier: License :: OSI Approved :: MIT License
Classifier: Operating System :: OS Independent
Classifier: Programming Language :: Python :: 3
Requires-Python: >=3.8
